vuegen/__init__.py
vuegen/__main__.py
vuegen/config_manager.py
vuegen/constants.py
vuegen/quarto_reportview.py
vuegen/report.py
vuegen/report_generator.py
vuegen/streamlit_reportview.py
vuegen/table_utils.py
vuegen/utils/__init__.py
vuegen/utils/variables.py
vuegen-0.5.1.dist-info/METADATA
vuegen-0.5.1.dist-info/WHEEL
vuegen-0.5.1.dist-info/entry_points.txt
vuegen-0.5.1.dist-info/licenses/LICENSE.md
vuegen-0.5.1.dist-info/RECORD
