Metadata-Version: 2.4
Name: vuegen
Version: 0.5.1
Summary: VueGen automates the creation of reports from bioinformatics outputs, supporting formats like PDF, HTML, DOCX, ODT, PPTX, Reveal.js, Jupyter notebooks, and Streamlit web applications. Users simply provide a directory with output files and VueGen compiles them into a structured report.
License: MIT
License-File: LICENSE.md
Author: MoNA group
Requires-Python: >=3.9, !=2.7.*, !=3.0.*, !=3.1.*, !=3.2.*, !=3.3.*, !=3.4.*, !=3.5.*, !=3.6.*, !=3.7.*, !=3.8.*
Classifier: License :: OSI Approved :: MIT License
Classifier: Programming Language :: Python :: 3
Classifier: Programming Language :: Python :: 3.9
Classifier: Programming Language :: Python :: 3.10
Classifier: Programming Language :: Python :: 3.11
Classifier: Programming Language :: Python :: 3.12
Classifier: Programming Language :: Python :: 3.13
Classifier: Programming Language :: Python :: 3.14
Provides-Extra: docs
Provides-Extra: gui
Requires-Dist: altair[save]
Requires-Dist: customtkinter ; extra == "gui"
Requires-Dist: dataframe-image (>=0.2.6,<0.3.0)
Requires-Dist: ipywidgets ; extra == "docs"
Requires-Dist: itables (>=2.2.2,<3.0.0)
Requires-Dist: jupytext ; extra == "docs"
Requires-Dist: kaleido (==0.2.0)
Requires-Dist: matplotlib (>=3.9.2,<4.0.0)
Requires-Dist: myst-nb ; extra == "docs"
Requires-Dist: nbclient (>=0.10.0,<0.11.0)
Requires-Dist: nbformat (>=5.10.4,<6.0.0)
Requires-Dist: openpyxl (>=3.1.5,<4.0.0)
Requires-Dist: pandas[parquet] (>=2.2.3,<3.0.0)
Requires-Dist: plotly (==5.15.0)
Requires-Dist: pyvis (>=0.3.2,<0.4.0)
Requires-Dist: pyyaml (>=6.0.2,<7.0.0)
Requires-Dist: quarto-cli
Requires-Dist: sphinx ; extra == "docs"
Requires-Dist: sphinx-book-theme ; extra == "docs"
Requires-Dist: sphinx-copybutton ; extra == "docs"
Requires-Dist: sphinx-new-tab-link (!=0.2.2) ; extra == "docs"
Requires-Dist: streamlit (==1.39.0)
Requires-Dist: streamlit-aggrid
Requires-Dist: strenum (>=0.4.15,<0.5.0) ; python_version < "3.11"
Requires-Dist: vl-convert-python (>=1.7.0,<2.0.0)
Requires-Dist: xlrd (>=2.0.1,<3.0.0)
Project-URL: Repository, https://github.com/Multiomics-Analytics-Group/vuegen
